langchain_nebius/__init__.py
langchain_nebius/chat_models.py
langchain_nebius/embeddings.py
langchain_nebius/retrievers.py
langchain_nebius/tools.py
langchain_nebius-0.1.3.dist-info/LICENSE
langchain_nebius-0.1.3.dist-info/METADATA
langchain_nebius-0.1.3.dist-info/WHEEL
langchain_nebius-0.1.3.dist-info/RECORD
