Metadata-Version: 2.3
Name: langchain-nebius
Version: 0.1.3
Summary: LangChain integration for Nebius AI Studio
License: MIT
Keywords: langchain,nebius,llm,ai,embeddings,retrieval,rag
Author: Akim Tsvigun
Author-email: aktsvigun@nebius.com
Requires-Python: >=3.8.1,<4.0
Classifier: Development Status :: 4 - Beta
Classifier: Intended Audience :: Developers
Classifier: License :: OSI Approved :: MIT License
Classifier: Programming Language :: Python :: 3
Classifier: Programming Language :: Python :: 3.9
Classifier: Programming Language :: Python :: 3.10
Classifier: Programming Language :: Python :: 3.11
Classifier: Programming Language :: Python :: 3.12
Classifier: Programming Language :: Python :: 3.13
Classifier: Programming Language :: Python :: 3.8
Classifier: Topic :: Software Development :: Libraries :: Python Modules
Requires-Dist: langchain-core (>=0.3.35)
Requires-Dist: langchain_openai (>=0.3.5)
Requires-Dist: openai (>=1.0.0)
Project-URL: Repository, https://github.com/nebius/langchain-nebius
